amongusbot/__init__.py
amongusbot/au_cog.py
amongusbot/bot.py
amongusbot/config.py
amongusbot/utils.py
amongusbot-0.2.1.dist-info/WHEEL
amongusbot-0.2.1.dist-info/METADATA
amongusbot-0.2.1.dist-info/RECORD
