Metadata-Version: 2.1
Name: amongusbot
Version: 0.2.1
Summary: Bot for mass-muting users in a Discord channel whenever a hotkey is pressed.
Home-page: https://github.com/PederHA/amongusbot
Author: PederHA
Author-email: peder.andresen@gmail.com
Requires-Python: >=3.8,<4.0
Classifier: Programming Language :: Python :: 3
Classifier: Programming Language :: Python :: 3.8
Requires-Dist: discord.py (>=1.4.1,<2.0.0)
Requires-Dist: keyboard (>=0.13.5,<0.14.0)
